loopsolver/__init__.py
loopsolver/admm_constant_norm.py
loopsolver/admm_method.py
loopsolver/admm_solver.py
loopsolver/version.py
loopsolver-0.1.0.dist-info/METADATA
loopsolver-0.1.0.dist-info/WHEEL
loopsolver-0.1.0.dist-info/top_level.txt
loopsolver-0.1.0.dist-info/RECORD
